rtl.sv
// Code your design here
module comparator_4bit (
    input  logic [3:0] a,
    input  logic [3:0] b,
    output logic gt,
    output logic lt,
    output logic eq
);

    always_comb begin
        gt = (a > b);
        lt = (a < b);
        eq = (a == b);
    end

endmodule

tb.sv
class transaction;
        rand bit [3:0] a;
        rand bit [3:0] b;

        constraint valid_range {
            a inside {[0:15]};
            b inside {[0:15]};
        }
    endclass



module tb;

    logic clk;
    logic [3:0] a, b;
    logic gt, lt, eq;

    // DUT
    comparator_4bit dut (
        .a(a),
        .b(b),
        .gt(gt),
        .lt(lt),
        .eq(eq)
    );

    // Clock generation
    always #5 clk = ~clk;
    

    transaction tr;

    // -----------------------------
    // Functional Coverage
    // -----------------------------
    covergroup cg @(posedge clk);
        coverpoint a;
        coverpoint b;

        compare_result : coverpoint {gt,lt,eq} {
            bins greater = {3'b100};
            bins lesser  = {3'b010};
            bins equal   = {3'b001};
        }

        cross a,b;
    endgroup

    cg coverage = new();

    // -----------------------------
    // Assertions
    // -----------------------------

    // Only one output high at a time
    property one_hot_check;
        @(posedge clk)
        (gt + lt + eq) == 1;
    endproperty

    assert property (one_hot_check)
        else $error("ERROR: Outputs not one-hot!");

    // Correct behavior assertion
    property functional_check;
        @(posedge clk)
        (a > b) |-> gt;
    endproperty

    assert property (functional_check)
        else $error("ERROR: Functional mismatch!");

    // -----------------------------
    // Scoreboard
    // -----------------------------
    task check_result();
        if (a > b && gt !== 1) $error("Mismatch: A>B failed");
        if (a < b && lt !== 1) $error("Mismatch: A<B failed");
        if (a == b && eq !== 1) $error("Mismatch: A==B failed");
    endtask

    // -----------------------------
    // Test Sequence
    // -----------------------------
    initial begin
      $dumpfile("dump.vcd");
		$dumpvars(0, tb);
        clk = 0;
        tr = new();

      repeat (500) begin
            assert(tr.randomize());
            a = tr.a;
            b = tr.b;
            #10;
            check_result();
            coverage.sample();
        end

        $display("Coverage = %0.2f %%", coverage.get_coverage());
        $finish;
    end

endmodule

dump.vcd
$date
Thu Feb 26 05:50:24 2026
$end
$version
Riviera-PRO Version 2025.04.139.9738
$end
$timescale
1 ps
$end

$scope module tb $end
$var reg 1 ! clk $end
$var reg 4 " a [3:0] $end
$var reg 4 # b [3:0] $end
$var reg 1 $ gt $end
$var reg 1 % lt $end
$var reg 1 & eq $end

$scope module dut $end
$var wire 4 ' a [3:0] $end
$var wire 4 ( b [3:0] $end
$var reg 1 ) gt $end
$var reg 1 * lt $end
$var reg 1 + eq $end
$upscope $end

$upscope $end

$enddefinitions $end
$dumpvars
0!
b11 "
b1 #
1$
0%
0&
b11 '
b1 (
1)
0*
0+
$end
#5
1!
#10
b1 "
b1100 #
0!
b1100 (
b1 '
0)
1*
0$
1%
#15
1!
#20
b101 "
b1110 #
0!
b1110 (
b101 '
#25
1!
#30
b0 "
b1100 #
0!
b1100 (
b0 '
#35
1!
#40
b10 "
b0 #
0!
b0 (
b10 '
1)
0*
1$
0%
#45
1!
#50
b101 "
0!
b101 '
#55
1!
#60
b10 "
b1100 #
0!
b1100 (
b10 '
0)
1*
0$
1%
#65
1!
#70
b101 "
b1111 #
0!
b1111 (
b101 '
#75
1!
#80
b10 "
b101 #
0!
b101 (
b10 '
#85
1!
#90
b100 "
b110 #
0!
b110 (
b100 '
#95
1!
#100
b10 "
b11 #
0!
b11 (
b10 '
#105
1!
#110
b11 "
b1000 #
0!
b1000 (
b11 '
#115
1!
#120
b1100 "
b1100 #
0!
b1100 (
b1100 '
0*
1+
0%
1&
#125
1!
#130
b111 "
b0 #
0!
b0 (
b111 '
1)
0+
1$
0&
#135
1!
#140
b1 "
b1110 #
0!
b1110 (
b1 '
0)
1*
0$
1%
#145
1!
#150
b10 "
b10 #
0!
b10 (
b10 '
0*
1+
0%
1&
#155
1!
#160
b1110 #
0!
b1110 (
1*
0+
1%
0&
#165
1!
#170
b0 "
b1111 #
0!
b1111 (
b0 '
#175
1!
#180
b1000 "
b1011 #
0!
b1011 (
b1000 '
#185
1!
#190
b1111 "
b111 #
0!
b111 (
b1111 '
1)
0*
1$
0%
#195
1!
#200
b0 "
b1100 #
0!
b1100 (
b0 '
0)
1*
0$
1%
#205
1!
#210
b1100 "
b1001 #
0!
b1001 (
b1100 '
1)
0*
1$
0%
#215
1!
#220
b111 "
b1000 #
0!
b1000 (
b111 '
0)
1*
0$
1%
#225
1!
#230
b110 "
b110 #
0!
b110 (
b110 '
0*
1+
0%
1&
#235
1!
#240
b1101 "
b100 #
0!
b100 (
b1101 '
1)
0+
1$
0&
#245
1!
#250
b1 "
0!
b1 '
0)
1*
0$
1%
#255
1!
#260
b1001 "
b110 #
0!
b110 (
b1001 '
1)
0*
1$
0%
#265
1!
#270
b1010 "
b1110 #
0!
b1110 (
b1010 '
0)
1*
0$
1%
#275
1!
#280
b1001 "
b1001 #
0!
b1001 (
b1001 '
0*
1+
0%
1&
#285
1!
#290
b10 "
b1000 #
0!
b1000 (
b10 '
1*
0+
1%
0&
#295
1!
#300
b100 "
b1001 #
0!
b1001 (
b100 '
#305
1!
#310
b1001 "
b1 #
0!
b1 (
b1001 '
1)
0*
1$
0%
#315
1!
#320
b1111 "
b1110 #
0!
b1110 (
b1111 '
#325
1!
#330
b1000 "
b1 #
0!
b1 (
b1000 '
#335
1!
#340
b110 #
0!
b110 (
#345
1!
#350
b1010 "
b10 #
0!
b10 (
b1010 '
#355
1!
#360
b10 "
b1011 #
0!
b1011 (
b10 '
0)
1*
0$
1%
#365
1!
#370
b1000 "
0!
b1000 '
#375
1!
#380
b1101 "
b100 #
0!
b100 (
b1101 '
1)
0*
1$
0%
#385
1!
#390
b0 "
b110 #
0!
b110 (
b0 '
0)
1*
0$
1%
#395
1!
#400
b1 "
0!
b1 '
#405
1!
#410
b11 #
0!
b11 (
#415
1!
#420
b111 "
b1011 #
0!
b1011 (
b111 '
#425
1!
#430
b110 "
b110 #
0!
b110 (
b110 '
0*
1+
0%
1&
#435
1!
#440
b100 "
b1011 #
0!
b1011 (
b100 '
1*
0+
1%
0&
#445
1!
#450
b1100 "
b1100 #
0!
b1100 (
b1100 '
0*
1+
0%
1&
#455
1!
#460
b11 "
b111 #
0!
b111 (
b11 '
1*
0+
1%
0&
#465
1!
#470
b10 "
b1011 #
0!
b1011 (
b10 '
#475
1!
#480
b1110 "
b101 #
0!
b101 (
b1110 '
1)
0*
1$
0%
#485
1!
#490
b1100 "
b111 #
0!
b111 (
b1100 '
#495
1!
#500
b1001 "
b101 #
0!
b101 (
b1001 '
#505
1!
#510
b100 "
b0 #
0!
b0 (
b100 '
#515
1!
#520
b1011 "
b1 #
0!
b1 (
b1011 '
#525
1!
#530
b1101 "
b1001 #
0!
b1001 (
b1101 '
#535
1!
#540
b1001 "
b11 #
0!
b11 (
b1001 '
#545
1!
#550
b101 "
b100 #
0!
b100 (
b101 '
#555
1!
#560
b1 "
b1 #
0!
b1 (
b1 '
0)
1+
0$
1&
#565
1!
#570
b111 "
b1000 #
0!
b1000 (
b111 '
1*
0+
1%
0&
#575
1!
#580
b0 "
b100 #
0!
b100 (
b0 '
#585
1!
#590
b1010 "
b101 #
0!
b101 (
b1010 '
1)
0*
1$
0%
#595
1!
#600
b0 "
b111 #
0!
b111 (
b0 '
0)
1*
0$
1%
#605
1!
#610
b1010 "
b1110 #
0!
b1110 (
b1010 '
#615
1!
#620
b10 "
b1010 #
0!
b1010 (
b10 '
#625
1!
#630
b1 "
b100 #
0!
b100 (
b1 '
#635
1!
#640
b100 "
b101 #
0!
b101 (
b100 '
#645
1!
#650
b1 "
b100 #
0!
b100 (
b1 '
#655
1!
#660
b1111 "
b1010 #
0!
b1010 (
b1111 '
1)
0*
1$
0%
#665
1!
#670
b1 "
b111 #
0!
b111 (
b1 '
0)
1*
0$
1%
#675
1!
#680
b1111 "
b11 #
0!
b11 (
b1111 '
1)
0*
1$
0%
#685
1!
#690
b1 "
b1000 #
0!
b1000 (
b1 '
0)
1*
0$
1%
#695
1!
#700
b1111 "
b1011 #
0!
b1011 (
b1111 '
1)
0*
1$
0%
#705
1!
#710
b1011 "
b10 #
0!
b10 (
b1011 '
#715
1!
#720
b1 "
b1001 #
0!
b1001 (
b1 '
0)
1*
0$
1%
#725
1!
#730
b1000 "
b111 #
0!
b111 (
b1000 '
1)
0*
1$
0%
#735
1!
#740
b110 #
0!
b110 (
#745
1!
#750
b1100 "
b1101 #
0!
b1101 (
b1100 '
0)
1*
0$
1%
#755
1!
#760
b10 "
b1111 #
0!
b1111 (
b10 '
#765
1!
#770
b0 "
b10 #
0!
b10 (
b0 '
#775
1!
#780
b101 "
b111 #
0!
b111 (
b101 '
#785
1!
#790
b1010 "
b1 #
0!
b1 (
b1010 '
1)
0*
1$
0%
#795
1!
#800
b100 "
b100 #
0!
b100 (
b100 '
0)
1+
0$
1&
#805
1!
#810
b1011 "
b1101 #
0!
b1101 (
b1011 '
1*
0+
1%
0&
#815
1!
#820
b1101 "
b1001 #
0!
b1001 (
b1101 '
1)
0*
1$
0%
#825
1!
#830
b101 "
b1010 #
0!
b1010 (
b101 '
0)
1*
0$
1%
#835
1!
#840
b11 "
b100 #
0!
b100 (
b11 '
#845
1!
#850
b110 "
b1011 #
0!
b1011 (
b110 '
#855
1!
#860
b100 "
b1110 #
0!
b1110 (
b100 '
#865
1!
#870
b101 "
b101 #
0!
b101 (
b101 '
0*
1+
0%
1&
#875
1!
#880
b110 "
b0 #
0!
b0 (
b110 '
1)
0+
1$
0&
#885
1!
#890
b1000 "
b11 #
0!
b11 (
b1000 '
#895
1!
#900
b10 "
b101 #
0!
b101 (
b10 '
0)
1*
0$
1%
#905
1!
#910
b0 "
b11 #
0!
b11 (
b0 '
#915
1!
#920
b1101 "
b1010 #
0!
b1010 (
b1101 '
1)
0*
1$
0%
#925
1!
#930
b1 "
b1110 #
0!
b1110 (
b1 '
0)
1*
0$
1%
#935
1!
#940
b1111 "
b1 #
0!
b1 (
b1111 '
1)
0*
1$
0%
#945
1!
#950
b10 "
b100 #
0!
b100 (
b10 '
0)
1*
0$
1%
#955
1!
#960
b101 #
0!
b101 (
#965
1!
#970
b1101 "
0!
b1101 '
1)
0*
1$
0%
#975
1!
#980
b1001 "
b1000 #
0!
b1000 (
b1001 '
#985
1!
#990
b100 "
b1101 #
0!
b1101 (
b100 '
0)
1*
0$
1%
#995
1!
#1000
b1010 "
b1000 #
0!
b1000 (
b1010 '
1)
0*
1$
0%
#1005
1!
#1010
b1 "
b111 #
0!
b111 (
b1 '
0)
1*
0$
1%
#1015
1!
#1020
b1010 "
b1 #
0!
b1 (
b1010 '
1)
0*
1$
0%
#1025
1!
#1030
b111 "
b10 #
0!
b10 (
b111 '
#1035
1!
#1040
b11 "
b1100 #
0!
b1100 (
b11 '
0)
1*
0$
1%
#1045
1!
#1050
b1010 "
b1 #
0!
b1 (
b1010 '
1)
0*
1$
0%
#1055
1!
#1060
b100 "
b100 #
0!
b100 (
b100 '
0)
1+
0$
1&
#1065
1!
#1070
b1000 "
b1011 #
0!
b1011 (
b1000 '
1*
0+
1%
0&
#1075
1!
#1080
b101 "
b1001 #
0!
b1001 (
b101 '
#1085
1!
#1090
b11 "
b11 #
0!
b11 (
b11 '
0*
1+
0%
1&
#1095
1!
#1100
b110 "
b1110 #
0!
b1110 (
b110 '
1*
0+
1%
0&
#1105
1!
#1110
b1100 "
b11 #
0!
b11 (
b1100 '
1)
0*
1$
0%
#1115
1!
#1120
b11 "
b1100 #
0!
b1100 (
b11 '
0)
1*
0$
1%
#1125
1!
#1130
b1101 "
b1 #
0!
b1 (
b1101 '
1)
0*
1$
0%
#1135
1!
#1140
b110 "
b1010 #
0!
b1010 (
b110 '
0)
1*
0$
1%
#1145
1!
#1150
b10 "
b100 #
0!
b100 (
b10 '
#1155
1!
#1160
b1001 "
0!
b1001 '
1)
0*
1$
0%
#1165
1!
#1170
b101 "
b1111 #
0!
b1111 (
b101 '
0)
1*
0$
1%
#1175
1!
#1180
b110 "
b1000 #
0!
b1000 (
b110 '
#1185
1!
#1190
b101 "
b1011 #
0!
b1011 (
b101 '
#1195
1!
#1200
b1101 "
b0 #
0!
b0 (
b1101 '
1)
0*
1$
0%
#1205
1!
#1210
b11 "
b100 #
0!
b100 (
b11 '
0)
1*
0$
1%
#1215
1!
#1220
b1 "
b1001 #
0!
b1001 (
b1 '
#1225
1!
#1230
b1001 "
b1010 #
0!
b1010 (
b1001 '
#1235
1!
#1240
b1111 "
b10 #
0!
b10 (
b1111 '
1)
0*
1$
0%
#1245
1!
#1250
b111 "
b111 #
0!
b111 (
b111 '
0)
1+
0$
1&
#1255
1!
#1260
b1100 "
b0 #
0!
b0 (
b1100 '
1)
0+
1$
0&
#1265
1!
#1270
b1011 "
0!
b1011 '
#1275
1!
#1280
b1010 "
b1110 #
0!
b1110 (
b1010 '
0)
1*
0$
1%
#1285
1!
#1290
b1100 "
b101 #
0!
b101 (
b1100 '
1)
0*
1$
0%
#1295
1!
#1300
b111 "
b10 #
0!
b10 (
b111 '
#1305
1!
#1310
b100 "
0!
b100 '
#1315
1!
#1320
b11 "
b1011 #
0!
b1011 (
b11 '
0)
1*
0$
1%
#1325
1!
#1330
b111 "
b1000 #
0!
b1000 (
b111 '
#1335
1!
#1340
b1011 "
b110 #
0!
b110 (
b1011 '
1)
0*
1$
0%
#1345
1!
#1350
b100 "
0!
b100 '
0)
1*
0$
1%
#1355
1!
#1360
b111 "
b0 #
0!
b0 (
b111 '
1)
0*
1$
0%
#1365
1!
#1370
0!
#1375
1!
#1380
b1100 "
b110 #
0!
b110 (
b1100 '
#1385
1!
#1390
b1000 "
b10 #
0!
b10 (
b1000 '
#1395
1!
#1400
b1110 "
b1000 #
0!
b1000 (
b1110 '
#1405
1!
#1410
b100 "
b1110 #
0!
b1110 (
b100 '
0)
1*
0$
1%
#1415
1!
#1420
b110 "
b1100 #
0!
b1100 (
b110 '
#1425
1!
#1430
b101 "
b1 #
0!
b1 (
b101 '
1)
0*
1$
0%
#1435
1!
#1440
b1100 "
b1110 #
0!
b1110 (
b1100 '
0)
1*
0$
1%
#1445
1!
#1450
b1 "
b11 #
0!
b11 (
b1 '
#1455
1!
#1460
b10 "
b101 #
0!
b101 (
b10 '
#1465
1!
#1470
b1100 "
b1101 #
0!
b1101 (
b1100 '
#1475
1!
#1480
b1 #
0!
b1 (
1)
0*
1$
0%
#1485
1!
#1490
b1011 "
b101 #
0!
b101 (
b1011 '
#1495
1!
#1500
b1111 "
b1 #
0!
b1 (
b1111 '
#1505
1!
#1510
b110 "
b101 #
0!
b101 (
b110 '
#1515
1!
#1520
b101 "
b1 #
0!
b1 (
b101 '
#1525
1!
#1530
b1001 "
b1010 #
0!
b1010 (
b1001 '
0)
1*
0$
1%
#1535
1!
#1540
b1010 "
b0 #
0!
b0 (
b1010 '
1)
0*
1$
0%
#1545
1!
#1550
b1000 "
b1000 #
0!
b1000 (
b1000 '
0)
1+
0$
1&
#1555
1!
#1560
b111 "
b1111 #
0!
b1111 (
b111 '
1*
0+
1%
0&
#1565
1!
#1570
b1100 "
b1011 #
0!
b1011 (
b1100 '
1)
0*
1$
0%
#1575
1!
#1580
b1000 "
b101 #
0!
b101 (
b1000 '
#1585
1!
#1590
b1110 "
b1000 #
0!
b1000 (
b1110 '
#1595
1!
#1600
b1100 "
b0 #
0!
b0 (
b1100 '
#1605
1!
#1610
b1110 "
b10 #
0!
b10 (
b1110 '
#1615
1!
#1620
b1001 "
b111 #
0!
b111 (
b1001 '
#1625
1!
#1630
b0 "
b1000 #
0!
b1000 (
b0 '
0)
1*
0$
1%
#1635
1!
#1640
b1001 "
b1010 #
0!
b1010 (
b1001 '
#1645
1!
#1650
b100 "
b1011 #
0!
b1011 (
b100 '
#1655
1!
#1660
b101 "
0!
b101 '
#1665
1!
#1670
b1 "
b1110 #
0!
b1110 (
b1 '
#1675
1!
#1680
b1100 "
b101 #
0!
b101 (
b1100 '
1)
0*
1$
0%
#1685
1!
#1690
b1110 "
b110 #
0!
b110 (
b1110 '
#1695
1!
#1700
b0 "
b1010 #
0!
b1010 (
b0 '
0)
1*
0$
1%
#1705
1!
#1710
b1101 "
b1 #
0!
b1 (
b1101 '
1)
0*
1$
0%
#1715
1!
#1720
b1100 #
0!
b1100 (
#1725
1!
#1730
b11 "
b11 #
0!
b11 (
b11 '
0)
1+
0$
1&
#1735
1!
#1740
b111 "
b1 #
0!
b1 (
b111 '
1)
0+
1$
0&
#1745
1!
#1750
b1000 "
b1011 #
0!
b1011 (
b1000 '
0)
1*
0$
1%
#1755
1!
#1760
b1111 "
b1001 #
0!
b1001 (
b1111 '
1)
0*
1$
0%
#1765
1!
#1770
b1000 "
b100 #
0!
b100 (
b1000 '
#1775
1!
#1780
b1 "
b1011 #
0!
b1011 (
b1 '
0)
1*
0$
1%
#1785
1!
#1790
b11 "
b111 #
0!
b111 (
b11 '
#1795
1!
#1800
b1101 "
b1011 #
0!
b1011 (
b1101 '
1)
0*
1$
0%
#1805
1!
#1810
b111 "
b1110 #
0!
b1110 (
b111 '
0)
1*
0$
1%
#1815
1!
#1820
b0 "
b1001 #
0!
b1001 (
b0 '
#1825
1!
#1830
b1000 "
b11 #
0!
b11 (
b1000 '
1)
0*
1$
0%
#1835
1!
#1840
b1111 "
0!
b1111 '
#1845
1!
#1850
b1010 "
b111 #
0!
b111 (
b1010 '
#1855
1!
#1860
b0 "
b1010 #
0!
b1010 (
b0 '
0)
1*
0$
1%
#1865
1!
#1870
b1011 "
b1111 #
0!
b1111 (
b1011 '
#1875
1!
#1880
b100 "
b1 #
0!
b1 (
b100 '
1)
0*
1$
0%
#1885
1!
#1890
b1111 "
b1001 #
0!
b1001 (
b1111 '
#1895
1!
#1900
b101 "
b10 #
0!
b10 (
b101 '
#1905
1!
#1910
b1000 "
b1100 #
0!
b1100 (
b1000 '
0)
1*
0$
1%
#1915
1!
#1920
0!
#1925
1!
#1930
b10 "
b1101 #
0!
b1101 (
b10 '
#1935
1!
#1940
b1110 "
b111 #
0!
b111 (
b1110 '
1)
0*
1$
0%
#1945
1!
#1950
b1001 "
b1110 #
0!
b1110 (
b1001 '
0)
1*
0$
1%
#1955
1!
#1960
b1101 "
b111 #
0!
b111 (
b1101 '
1)
0*
1$
0%
#1965
1!
#1970
b1000 "
b1 #
0!
b1 (
b1000 '
#1975
1!
#1980
b110 "
b1110 #
0!
b1110 (
b110 '
0)
1*
0$
1%
#1985
1!
#1990
b1111 "
b1010 #
0!
b1010 (
b1111 '
1)
0*
1$
0%
#1995
1!
#2000
b11 "
b1100 #
0!
b1100 (
b11 '
0)
1*
0$
1%
#2005
1!
#2010
b0 "
b10 #
0!
b10 (
b0 '
#2015
1!
#2020
b1111 "
0!
b1111 '
1)
0*
1$
0%
#2025
1!
#2030
b110 "
b1000 #
0!
b1000 (
b110 '
0)
1*
0$
1%
#2035
1!
#2040
b1 "
b101 #
0!
b101 (
b1 '
#2045
1!
#2050
b10 "
b10 #
0!
b10 (
b10 '
0*
1+
0%
1&
#2055
1!
#2060
b110 "
b1101 #
0!
b1101 (
b110 '
1*
0+
1%
0&
#2065
1!
#2070
b11 "
b1 #
0!
b1 (
b11 '
1)
0*
1$
0%
#2075
1!
#2080
b1011 "
b1101 #
0!
b1101 (
b1011 '
0)
1*
0$
1%
#2085
1!
#2090
b1 "
b10 #
0!
b10 (
b1 '
#2095
1!
#2100
b100 "
b1101 #
0!
b1101 (
b100 '
#2105
1!
#2110
b111 "
b1 #
0!
b1 (
b111 '
1)
0*
1$
0%
#2115
1!
#2120
b1100 "
b10 #
0!
b10 (
b1100 '
#2125
1!
#2130
b1011 "
b1000 #
0!
b1000 (
b1011 '
#2135
1!
#2140
b1001 "
b0 #
0!
b0 (
b1001 '
#2145
1!
#2150
b1010 "
b110 #
0!
b110 (
b1010 '
#2155
1!
#2160
b1011 "
0!
b1011 '
#2165
1!
#2170
b101 "
b1010 #
0!
b1010 (
b101 '
0)
1*
0$
1%
#2175
1!
#2180
b1 "
b111 #
0!
b111 (
b1 '
#2185
1!
#2190
b10 "
b1110 #
0!
b1110 (
b10 '
#2195
1!
#2200
b111 "
b1001 #
0!
b1001 (
b111 '
#2205
1!
#2210
b1 "
b1 #
0!
b1 (
b1 '
0*
1+
0%
1&
#2215
1!
#2220
b0 "
b110 #
0!
b110 (
b0 '
1*
0+
1%
0&
#2225
1!
#2230
b1100 "
b1101 #
0!
b1101 (
b1100 '
#2235
1!
#2240
b1101 "
b0 #
0!
b0 (
b1101 '
1)
0*
1$
0%
#2245
1!
#2250
b1001 "
b111 #
0!
b111 (
b1001 '
#2255
1!
#2260
b111 "
b10 #
0!
b10 (
b111 '
#2265
1!
#2270
b1111 "
b100 #
0!
b100 (
b1111 '
#2275
1!
#2280
b1110 "
b1 #
0!
b1 (
b1110 '
#2285
1!
#2290
b11 "
b1000 #
0!
b1000 (
b11 '
0)
1*
0$
1%
#2295
1!
#2300
b1110 "
b1 #
0!
b1 (
b1110 '
1)
0*
1$
0%
#2305
1!
#2310
b1010 #
0!
b1010 (
#2315
1!
#2320
b1011 "
b100 #
0!
b100 (
b1011 '
#2325
1!
#2330
b1100 "
0!
b1100 '
#2335
1!
#2340
b1010 "
b1101 #
0!
b1101 (
b1010 '
0)
1*
0$
1%
#2345
1!
#2350
b100 "
b111 #
0!
b111 (
b100 '
#2355
1!
#2360
b1011 "
b11 #
0!
b11 (
b1011 '
1)
0*
1$
0%
#2365
1!
#2370
b1111 "
b1011 #
0!
b1011 (
b1111 '
#2375
1!
#2380
b110 "
b1 #
0!
b1 (
b110 '
#2385
1!
#2390
b111 "
b11 #
0!
b11 (
b111 '
#2395
1!
#2400
b1 "
b1010 #
0!
b1010 (
b1 '
0)
1*
0$
1%
#2405
1!
#2410
b1101 "
b1111 #
0!
b1111 (
b1101 '
#2415
1!
#2420
b1011 "
b1001 #
0!
b1001 (
b1011 '
1)
0*
1$
0%
#2425
1!
#2430
b111 "
b1011 #
0!
b1011 (
b111 '
0)
1*
0$
1%
#2435
1!
#2440
b1000 "
b111 #
0!
b111 (
b1000 '
1)
0*
1$
0%
#2445
1!
#2450
b100 "
b101 #
0!
b101 (
b100 '
0)
1*
0$
1%
#2455
1!
#2460
b1010 "
b110 #
0!
b110 (
b1010 '
1)
0*
1$
0%
#2465
1!
#2470
b1101 "
b1100 #
0!
b1100 (
b1101 '
#2475
1!
#2480
b1000 "
b1010 #
0!
b1010 (
b1000 '
0)
1*
0$
1%
#2485
1!
#2490
b1010 "
b100 #
0!
b100 (
b1010 '
1)
0*
1$
0%
#2495
1!
#2500
b1101 "
b111 #
0!
b111 (
b1101 '
#2505
1!
#2510
b1110 "
b101 #
0!
b101 (
b1110 '
#2515
1!
#2520
b0 "
b110 #
0!
b110 (
b0 '
0)
1*
0$
1%
#2525
1!
#2530
b1 "
b11 #
0!
b11 (
b1 '
#2535
1!
#2540
b1100 "
b1 #
0!
b1 (
b1100 '
1)
0*
1$
0%
#2545
1!
#2550
b1000 "
b1001 #
0!
b1001 (
b1000 '
0)
1*
0$
1%
#2555
1!
#2560
b1011 "
b1110 #
0!
b1110 (
b1011 '
#2565
1!
#2570
b10 "
b1111 #
0!
b1111 (
b10 '
#2575
1!
#2580
b100 "
b1000 #
0!
b1000 (
b100 '
#2585
1!
#2590
b1 "
b1010 #
0!
b1010 (
b1 '
#2595
1!
#2600
b1101 "
b1000 #
0!
b1000 (
b1101 '
1)
0*
1$
0%
#2605
1!
#2610
b100 "
b10 #
0!
b10 (
b100 '
#2615
1!
#2620
b1111 "
b11 #
0!
b11 (
b1111 '
#2625
1!
#2630
b1101 "
b1111 #
0!
b1111 (
b1101 '
0)
1*
0$
1%
#2635
1!
#2640
b101 "
b1101 #
0!
b1101 (
b101 '
#2645
1!
#2650
b11 "
0!
b11 '
#2655
1!
#2660
b0 "
b1011 #
0!
b1011 (
b0 '
#2665
1!
#2670
b110 "
b1110 #
0!
b1110 (
b110 '
#2675
1!
#2680
b1011 "
b110 #
0!
b110 (
b1011 '
1)
0*
1$
0%
#2685
1!
#2690
b1110 #
0!
b1110 (
0)
1*
0$
1%
#2695
1!
#2700
b101 "
b1011 #
0!
b1011 (
b101 '
#2705
1!
#2710
b11 "
b10 #
0!
b10 (
b11 '
1)
0*
1$
0%
#2715
1!
#2720
b0 "
b0 #
0!
b0 (
b0 '
0)
1+
0$
1&
#2725
1!
#2730
b1100 "
b1010 #
0!
b1010 (
b1100 '
1)
0+
1$
0&
#2735
1!
#2740
b101 "
b1 #
0!
b1 (
b101 '
#2745
1!
#2750
b11 "
b101 #
0!
b101 (
b11 '
0)
1*
0$
1%
#2755
1!
#2760
b10 "
b1000 #
0!
b1000 (
b10 '
#2765
1!
#2770
b100 "
b100 #
0!
b100 (
b100 '
0*
1+
0%
1&
#2775
1!
#2780
b10 "
b1011 #
0!
b1011 (
b10 '
1*
0+
1%
0&
#2785
1!
#2790
b1 "
b111 #
0!
b111 (
b1 '
#2795
1!
#2800
b111 "
b1111 #
0!
b1111 (
b111 '
#2805
1!
#2810
b1011 "
b11 #
0!
b11 (
b1011 '
1)
0*
1$
0%
#2815
1!
#2820
b110 "
b1011 #
0!
b1011 (
b110 '
0)
1*
0$
1%
#2825
1!
#2830
b1111 "
b101 #
0!
b101 (
b1111 '
1)
0*
1$
0%
#2835
1!
#2840
b1110 "
b111 #
0!
b111 (
b1110 '
#2845
1!
#2850
b0 "
b0 #
0!
b0 (
b0 '
0)
1+
0$
1&
#2855
1!
#2860
b111 "
b11 #
0!
b11 (
b111 '
1)
0+
1$
0&
#2865
1!
#2870
b1101 "
b10 #
0!
b10 (
b1101 '
#2875
1!
#2880
b100 "
b100 #
0!
b100 (
b100 '
0)
1+
0$
1&
#2885
1!
#2890
b1110 "
0!
b1110 '
1)
0+
1$
0&
#2895
1!
#2900
b100 "
b1001 #
0!
b1001 (
b100 '
0)
1*
0$
1%
#2905
1!
#2910
b1 "
b1 #
0!
b1 (
b1 '
0*
1+
0%
1&
#2915
1!
#2920
b1010 "
b1100 #
0!
b1100 (
b1010 '
1*
0+
1%
0&
#2925
1!
#2930
b1011 "
b1110 #
0!
b1110 (
b1011 '
#2935
1!
#2940
b111 "
b100 #
0!
b100 (
b111 '
1)
0*
1$
0%
#2945
1!
#2950
b1101 "
b111 #
0!
b111 (
b1101 '
#2955
1!
#2960
b1 "
0!
b1 '
0)
1*
0$
1%
#2965
1!
#2970
b101 "
b1011 #
0!
b1011 (
b101 '
#2975
1!
#2980
b10 "
b1100 #
0!
b1100 (
b10 '
#2985
1!
#2990
b1101 "
b1101 #
0!
b1101 (
b1101 '
0*
1+
0%
1&
#2995
1!
#3000
b0 "
b1110 #
0!
b1110 (
b0 '
1*
0+
1%
0&
#3005
1!
#3010
b101 "
b1100 #
0!
b1100 (
b101 '
#3015
1!
#3020
b100 "
b1101 #
0!
b1101 (
b100 '
#3025
1!
#3030
b1000 "
b1100 #
0!
b1100 (
b1000 '
#3035
1!
#3040
b1001 "
b1111 #
0!
b1111 (
b1001 '
#3045
1!
#3050
b1101 "
b11 #
0!
b11 (
b1101 '
1)
0*
1$
0%
#3055
1!
#3060
b11 "
b100 #
0!
b100 (
b11 '
0)
1*
0$
1%
#3065
1!
#3070
b1101 "
b0 #
0!
b0 (
b1101 '
1)
0*
1$
0%
#3075
1!
#3080
b1010 "
b111 #
0!
b111 (
b1010 '
#3085
1!
#3090
b1011 "
b101 #
0!
b101 (
b1011 '
#3095
1!
#3100
b1 "
b0 #
0!
b0 (
b1 '
#3105
1!
#3110
b101 "
b101 #
0!
b101 (
b101 '
0)
1+
0$
1&
#3115
1!
#3120
b111 "
b110 #
0!
b110 (
b111 '
1)
0+
1$
0&
#3125
1!
#3130
b110 "
b1000 #
0!
b1000 (
b110 '
0)
1*
0$
1%
#3135
1!
#3140
b1010 "
b10 #
0!
b10 (
b1010 '
1)
0*
1$
0%
#3145
1!
#3150
b101 "
b1100 #
0!
b1100 (
b101 '
0)
1*
0$
1%
#3155
1!
#3160
b10 "
b1110 #
0!
b1110 (
b10 '
#3165
1!
#3170
b1101 "
b110 #
0!
b110 (
b1101 '
1)
0*
1$
0%
#3175
1!
#3180
b1 "
b1101 #
0!
b1101 (
b1 '
0)
1*
0$
1%
#3185
1!
#3190
b1010 "
b110 #
0!
b110 (
b1010 '
1)
0*
1$
0%
#3195
1!
#3200
b101 "
b100 #
0!
b100 (
b101 '
#3205
1!
#3210
b1101 "
b1000 #
0!
b1000 (
b1101 '
#3215
1!
#3220
b1000 "
b110 #
0!
b110 (
b1000 '
#3225
1!
#3230
b1100 "
b111 #
0!
b111 (
b1100 '
#3235
1!
#3240
b101 "
b1101 #
0!
b1101 (
b101 '
0)
1*
0$
1%
#3245
1!
#3250
b1001 "
b1100 #
0!
b1100 (
b1001 '
#3255
1!
#3260
b110 "
b100 #
0!
b100 (
b110 '
1)
0*
1$
0%
#3265
1!
#3270
b1101 "
0!
b1101 '
#3275
1!
#3280
b1110 "
b10 #
0!
b10 (
b1110 '
#3285
1!
#3290
b1 "
b1111 #
0!
b1111 (
b1 '
0)
1*
0$
1%
#3295
1!
#3300
b0 "
b0 #
0!
b0 (
b0 '
0*
1+
0%
1&
#3305
1!
#3310
b1001 "
b101 #
0!
b101 (
b1001 '
1)
0+
1$
0&
#3315
1!
#3320
b1011 "
b1100 #
0!
b1100 (
b1011 '
0)
1*
0$
1%
#3325
1!
#3330
b1110 "
b11 #
0!
b11 (
b1110 '
1)
0*
1$
0%
#3335
1!
#3340
b10 "
b110 #
0!
b110 (
b10 '
0)
1*
0$
1%
#3345
1!
#3350
b110 "
b11 #
0!
b11 (
b110 '
1)
0*
1$
0%
#3355
1!
#3360
b1100 "
b111 #
0!
b111 (
b1100 '
#3365
1!
